quadmompy/__init__.py
quadmompy/_version.py
quadmompy/core/__init__.py
quadmompy/core/hankel.py
quadmompy/core/io.py
quadmompy/core/quadrature.py
quadmompy/core/utils.py
quadmompy/core/inversion/__init__.py
quadmompy/core/inversion/basic.py
quadmompy/core/inversion/gwa.py
quadmompy/core/inversion/pd.py
quadmompy/core/inversion/wheeler.py
quadmompy/equations/__init__.py
quadmompy/equations/fpe_1d.py
quadmompy/equations/integrate_1d.py
quadmompy/moments/__init__.py
quadmompy/moments/correct.py
quadmompy/moments/randmom.py
quadmompy/moments/special.py
quadmompy/moments/transform.py
quadmompy/qbmm/__init__.py
quadmompy/qbmm/_eqmom_root_search.py
quadmompy/qbmm/multivariate.py
quadmompy/qbmm/qbmm.py
quadmompy/qbmm/univariate.py
quadmompy-0.9.7.dist-info/LICENSE.txt
quadmompy-0.9.7.dist-info/METADATA
quadmompy-0.9.7.dist-info/WHEEL
quadmompy-0.9.7.dist-info/top_level.txt
quadmompy-0.9.7.dist-info/RECORD
