Metadata-Version: 2.1
Name: quadmompy
Version: 0.9.7
Summary: Tools for moments, Gaussian quadrature, 
Author: Michele Puetz
Project-URL: Homepage, https://gitlab.com/puetzm/quadmompy.git
Classifier: Programming Language :: Python :: 3
Classifier: License :: OSI Approved :: GNU General Public License v3 or later (GPLv3+)
Classifier: Operating System :: OS Independent
License-File: LICENSE.txt
Requires-Dist: numpy (~=1.21.5)
Requires-Dist: scipy (~=1.8.0)
Provides-Extra: dev
Requires-Dist: pytest (>=6.2.5) ; extra == 'dev'
Requires-Dist: Sphinx (==4.3.2) ; extra == 'dev'
Requires-Dist: sphinxcontrib-bibtex (==2.5.0) ; extra == 'dev'
Requires-Dist: sphinxcontrib-packages (==1.0.1) ; extra == 'dev'
Requires-Dist: pylint (==2.12.2) ; extra == 'dev'
Requires-Dist: pylint-exit (==1.2.0) ; extra == 'dev'
